httptest/__init__.py
httptest/cli.py
httptest/httptest.py
httptest/oidc.py
tests/__init__.py
tests/test_httptest.py
httptest-2.1.1.dist-info/LICENSE
httptest-2.1.1.dist-info/METADATA
httptest-2.1.1.dist-info/WHEEL
httptest-2.1.1.dist-info/entry_points.txt
httptest-2.1.1.dist-info/top_level.txt
httptest-2.1.1.dist-info/RECORD
