Metadata-Version: 2.1
Name: httptest
Version: 2.1.1
Summary: Add unit tests to your http client
Home-page: https://github.com/pdxjohnny/httptest
Author: John Andersen
Author-email: johnandersenpdx@gmail.com
Maintainer: John Andersen
Maintainer-email: johnandersenpdx@gmail.com
License: MIT
Keywords: unittesting,testing,http,api,test
Classifier: Development Status :: 3 - Alpha
Classifier: Intended Audience :: Developers
Classifier: Environment :: Console
Classifier: License :: OSI Approved :: MIT License
Classifier: Natural Language :: English
Classifier: Operating System :: OS Independent
Classifier: Programming Language :: Python :: 3 :: Only
Classifier: Programming Language :: Python :: 3.6
Classifier: Programming Language :: Python :: 3.7
Classifier: Programming Language :: Python :: 3.8
Classifier: Programming Language :: Python :: 3.9
Classifier: Programming Language :: Python :: 3.10
Classifier: Programming Language :: Python :: Implementation :: CPython
Classifier: Programming Language :: Python :: Implementation :: PyPy
License-File: LICENSE
Provides-Extra: dev
Requires-Dist: build ; extra == 'dev'
Requires-Dist: twine ; extra == 'dev'
Requires-Dist: coverage ; extra == 'dev'
Requires-Dist: setuptools-scm[toml] >=3.4.3 ; extra == 'dev'
Requires-Dist: sbom4python ; extra == 'dev'
Provides-Extra: oidc
Requires-Dist: pyjwt[crypto] ; extra == 'oidc'
Requires-Dist: jwcrypto ; extra == 'oidc'
Requires-Dist: cryptography ; extra == 'oidc'
